flask_openapi/__init__.py
flask_openapi/__version__.py
flask_openapi/blueprint.py
flask_openapi/commands.py
flask_openapi/openapi.py
flask_openapi/plugins.py
flask_openapi/py.typed
flask_openapi/request.py
flask_openapi/scaffold.py
flask_openapi/templates.py
flask_openapi/types.py
flask_openapi/utils.py
flask_openapi/view.py
flask_openapi/models/__init__.py
flask_openapi/models/callback.py
flask_openapi/models/components.py
flask_openapi/models/contact.py
flask_openapi/models/data_type.py
flask_openapi/models/discriminator.py
flask_openapi/models/encoding.py
flask_openapi/models/example.py
flask_openapi/models/external_documentation.py
flask_openapi/models/file.py
flask_openapi/models/header.py
flask_openapi/models/info.py
flask_openapi/models/license.py
flask_openapi/models/link.py
flask_openapi/models/media_type.py
flask_openapi/models/oauth_flow.py
flask_openapi/models/oauth_flows.py
flask_openapi/models/operation.py
flask_openapi/models/parameter.py
flask_openapi/models/parameter_in_type.py
flask_openapi/models/path_item.py
flask_openapi/models/paths.py
flask_openapi/models/reference.py
flask_openapi/models/request_body.py
flask_openapi/models/response.py
flask_openapi/models/responses.py
flask_openapi/models/schema.py
flask_openapi/models/security_requirement.py
flask_openapi/models/security_scheme.py
flask_openapi/models/security_scheme_in_type.py
flask_openapi/models/server.py
flask_openapi/models/server_variable.py
flask_openapi/models/style_values.py
flask_openapi/models/tag.py
flask_openapi/models/validation_error.py
flask_openapi/models/xml.py
flask_openapi-4.3.1.dist-info/METADATA
flask_openapi-4.3.1.dist-info/WHEEL
flask_openapi-4.3.1.dist-info/licenses/LICENSE.rst
flask_openapi-4.3.1.dist-info/RECORD
