Metadata-Version: 2.4
Name: flask-openapi
Version: 4.3.1
Summary: Generate REST API and OpenAPI documentation for your Flask project.
Project-URL: Homepage, https://github.com/luolingchun/flask-openapi
Project-URL: Documentation, https://luolingchun.github.io/flask-openapi
Maintainer-email: llc <luolingchun@outlook.com>
License: MIT
License-File: LICENSE.rst
Classifier: Development Status :: 5 - Production/Stable
Classifier: Environment :: Web Environment
Classifier: Framework :: Flask
Classifier: Intended Audience :: Developers
Classifier: License :: OSI Approved :: MIT License
Classifier: Operating System :: OS Independent
Classifier: Programming Language :: Python
Classifier: Programming Language :: Python :: 3
Classifier: Programming Language :: Python :: 3 :: Only
Classifier: Programming Language :: Python :: 3.10
Classifier: Programming Language :: Python :: 3.11
Classifier: Programming Language :: Python :: 3.12
Classifier: Programming Language :: Python :: 3.13
Classifier: Programming Language :: Python :: 3.14
Requires-Python: >=3.10
Requires-Dist: flask>=2.0
Requires-Dist: pydantic>=2.4
Provides-Extra: async
Requires-Dist: asgiref>=3.2; extra == 'async'
Provides-Extra: dotenv
Requires-Dist: python-dotenv; extra == 'dotenv'
Provides-Extra: elements
Requires-Dist: flask-openapi-elements; extra == 'elements'
Provides-Extra: email
Requires-Dist: email-validator; extra == 'email'
Provides-Extra: rapidoc
Requires-Dist: flask-openapi-rapidoc; extra == 'rapidoc'
Provides-Extra: rapipdf
Requires-Dist: flask-openapi-rapipdf; extra == 'rapipdf'
Provides-Extra: redoc
Requires-Dist: flask-openapi-redoc; extra == 'redoc'
Provides-Extra: scalar
Requires-Dist: flask-openapi-scalar; extra == 'scalar'
Provides-Extra: swagger
Requires-Dist: flask-openapi-swagger; extra == 'swagger'
Provides-Extra: yaml
Requires-Dist: pyyaml; extra == 'yaml'
